[
  {
    "title":"Allamanda cathartica Plant",
    "coords":"10.9036130, 76.8978619"
  },
  {
    "title":"B-1421",
    "coords":"10.9037717, 76.8978602"
  },
  {
    "title":"B-1423",
    "coords":"10.9036792, 76.8978019"
  },
  {
    "title":"B-1424",
    "coords":"10.9036719, 76.8977841"
  },
  {
    "title":"B-1425",
    "coords":"10.9037022, 76.8978093"
  },
  {
    "title":"B-1426",
    "coords":"10.9037885, 76.8978002"
  },
  {
    "title":"B-1471",
    "coords":"10.9039040, 76.8978260"
  },
  {
    "title":"B-1472",
    "coords":"10.9039030, 76.8978609"
  },
  {
    "title":"B-1473",
    "coords":"10.9039468, 76.8978096"
  },
  {
    "title":"B-1484",
    "coords":"10.9041668, 76.8978146"
  },
  {
    "title":"B-1482",
    "coords":"10.9041862, 76.8978126"
  },
  {
    "title":"B-1486",
    "coords":"10.9042257, 76.8978200"
  },
  {
    "title":"tall tree",
    "coords":"10.9058181, 76.8985288"
  },
  {
    "title":"Royal palm trees center",
    "coords":"10.9058033, 76.8989636"
  },
  {
    "title":"Bismarck Nobilis",
    "coords":"10.9059814, 76.8990612"
  },
  {
    "title":"Bismarck Nobilis",
    "coords":"10.9059913, 76.8991514"
  },
  {
    "title":"Bismarck Nobilis",
    "coords":"10.9050122, 76.8994337"
  },
  {
    "title":"tree near shuttle bus",
    "coords":"10.9063238, 76.8992607"
  },
  {
    "title":"Narra",
    "coords":"10.9048854, 76.8993596"
  },
  {
    "title":"a",
    "coords":"10.9044045, 76.8995011"
  },
  {
    "title":"aa",
    "coords":"10.9038026, 76.9004228"
  },
  {
    "title":"Millettia pinnata, Indian beech tree",
    "coords":"10.9021710, 76.9012519"
  },
  {
    "title":"Saraca asoca, Asoka",
    "coords":"10.9023373, 76.9012958"
  },
  {
    "title":"Ficus elastica, Rubber fig",
    "coords":"10.9024064, 76.9013796"
  },
  {
    "title":"Bridelia airy-shawii, Spinous Kino Tree",
    "coords":"10.9017229, 76.9022074"
  },
  {
    "title":"Spathodea companulata, African tulip tree",
    "coords":"10.9015939, 76.9023278"
  },
  {
    "title":"Alstonia Scholaris, Devil tree (A-3094)",
    "coords":"10.9017074, 76.9027841"
  },
  {
    "title":"Strychnos nux-vomica, Nux vomica",
    "coords":"10.9017302, 76.9028518"
  },
  {
    "title":"Polyalthia longifolia, Indian Willow",
    "coords":"10.9017423, 76.9029809"
  },
  {
    "title":"Syzygium cumini, Jamul, Jamun",
    "coords":"10.9017502, 76.9030168"
  },
  {
    "title":"Artocarpus heterophyllus, Jack Tree",
    "coords":"10.9017572, 76.9030507"
  },
  {
    "title":"Callistemon viminalis, Bottle brush",
    "coords":"10.9017641, 76.9030738"
  },
  {
    "title":"Terminalla catappa, Indian almod",
    "coords":"10.9016791, 76.9030051"
  },
  {
    "title":"Terminalla catappa, Indian almod",
    "coords":"10.9017173, 76.9032615"
  },
  {
    "title":"Mangifera indica",
    "coords":"10.9017084, 76.9034198"
  },
  {
    "title":"Filicium decipiens, Fern tree",
    "coords":"10.9011626, 76.9026691"
  },
  {
    "title":"Millingtonia hortensia, Indian cork tree",
    "coords":"10.9012814, 76.9027529"
  },
  {
    "title":"Tabebuia Heterophylla, Cuban pink trumpet tree",
    "coords":"10.9010576, 76.9027191"
  },
  {
    "title":"Jambul, jamin",
    "coords":"10.9011504, 76.9028260"
  },
  {
    "title":"Grewia tilifolia, Dhaman",
    "coords":"10.9011781, 76.9028917"
  },
  {
    "title":"B-1413",
    "coords":"10.9034461, 76.8979394"
  },
  {
    "title":"B-1410",
    "coords":"10.9034141, 76.8979860"
  },
  {
    "title":"B-1409",
    "coords":"10.9034043, 76.8979930"
  },
  {
    "title":"B-1408",
    "coords":"10.9033924, 76.8979910"
  },
  {
    "title":"B-1407",
    "coords":"10.9033819, 76.8980007"
  },
  {
    "title":"B-1406",
    "coords":"10.9033779, 76.8979910"
  },
  {
    "title":"B-1403",
    "coords":"10.9033730, 76.8980208"
  },
  {
    "title":"B-1405",
    "coords":"10.9033615, 76.8980088"
  },
  {
    "title":"B-1404",
    "coords":"10.9033444, 76.8980141"
  },
  {
    "title":"B-1402",
    "coords":"10.9033621, 76.8980624"
  },
  {
    "title":"B-1401",
    "coords":"10.9033450, 76.8980715"
  },
  {
    "title":"B-1400",
    "coords":"10.9033114, 76.8980269"
  },
  {
    "title":"B-1390",
    "coords":"10.9032034, 76.8980923"
  },
  {
    "title":"B-1388",
    "coords":"10.9031498, 76.8981127"
  },
  {
    "title":"B-1385",
    "coords":"10.9031481, 76.8981523"
  },
  {
    "title":"B-1384",
    "coords":"10.9031550, 76.8982136"
  },
  {
    "title":"B-1383",
    "coords":"10.9031416, 76.8982683"
  },
  {
    "title":"B-1380",
    "coords":"10.9031386, 76.8982854"
  },
  {
    "title":"B-1379",
    "coords":"10.9031113, 76.8982897"
  },
  {
    "title":"Copper Pod",
    "coords":"10.8995724, 76.9000576"
  },
  {
    "title":"Yellow cheesewood",
    "coords":"10.8994302, 76.9001562"
  },
  {
    "title":"Devil Tree",
    "coords":"10.8995112, 76.9003047"
  },
  {
    "title":"Ceylon satinwood",
    "coords":"10.8994466, 76.9001321"
  },
  {
    "title":"Royal poinciana",
    "coords":"10.8995138, 76.9000798"
  },
  {
    "title":"Kindal, Flowering murdah",
    "coords":"10.8997011, 76.8999319"
  },
  {
    "title":"Notched leaf soap nut",
    "coords":"10.9015330, 76.8997167"
  },
  {
    "title":"Indian tulip tree",
    "coords":"10.8995141, 76.9003768"
  },
  {
    "title":"Spanish cherry",
    "coords":"10.8994796, 76.9004211"
  },
  {
    "title":"Indian beech tree",
    "coords":"10.8994243, 76.9004536"
  },
  {
    "title":"Neem, Margosa",
    "coords":"10.8992188, 76.9005143"
  },
  {
    "title":"Gold shower",
    "coords":"10.8992257, 76.9005954"
  },
  {
    "title":"Gold shower",
    "coords":"10.8992382, 76.9008717"
  },
  {
    "title":"Copper pod",
    "coords":"10.8991954, 76.9010273"
  },
  {
    "title":"Neem, Margosa",
    "coords":"10.8992185, 76.9011201"
  },
  {
    "title":"Ben teak",
    "coords":"10.8992073, 76.9012529"
  },
  {
    "title":"Neem, Margosa",
    "coords":"10.8992238, 76.9014574"
  },
  {
    "title":"Lebbeck tree",
    "coords":"10.8992300, 76.9014879"
  },
  {
    "title":"Neem, Margosa",
    "coords":"10.8992656, 76.9016586"
  },
  {
    "title":"Copper pod",
    "coords":"10.8992531, 76.9017384"
  },
  {
    "title":"Copper pod",
    "coords":"10.8992498, 76.9020794"
  },
  {
    "title":"Gold Shower",
    "coords":"10.8992425, 76.9021568"
  },
  {
    "title":"Indian beech tree",
    "coords":"10.8994875, 76.9021079"
  },
  {
    "title":"Pink Lapacho",
    "coords":"10.8995128, 76.9021501"
  },
  {
    "title":"Indian cherry",
    "coords":"10.8997202, 76.9020794"
  },
  {
    "title":"Yellow trumpet",
    "coords":"10.8995991, 76.9023241"
  },
  {
    "title":"Marking nut tree",
    "coords":"10.8996162, 76.9023724"
  },
  {
    "title":"Spanish cherry",
    "coords":"10.8996129, 76.9024113"
  },
  {
    "title":"Dinner plate tree",
    "coords":"10.8996113, 76.9024455"
  },
  {
    "title":"Blue Marble tree, Quandong",
    "coords":"10.8995355, 76.9024552"
  },
  {
    "title":"Child-life tree",
    "coords":"10.8997746, 76.9024173"
  },
  {
    "title":"Kigelia Africana",
    "coords":"10.8997196, 76.9024871"
  },
  {
    "title":"Weeping fig",
    "coords":"10.8999968, 76.9024448"
  },
  {
    "title":"Frangipani",
    "coords":"10.8999905, 76.9025551"
  },
  {
    "title":"Mango tree",
    "coords":"10.9019955, 76.9019288"
  },
  {
    "title":"West Indian Mahagony",
    "coords":"10.9020252, 76.9018993"
  },
  {
    "title":"Tamarind",
    "coords":"10.9020943, 76.9018893"
  },
  {
    "title":"Stereospermum colais",
    "coords":"10.9021996, 76.9018353"
  },
  {
    "title":"Yellow cheesewood",
    "coords":"10.9021996, 76.9018353"
  },
  {
    "title":"Indian cork tree",
    "coords":"10.9023504, 76.9018695"
  },
  {
    "title":"Belliric Myrobalan",
    "coords":"10.9023781, 76.9018504"
  },
  {
    "title":"Soapnut",
    "coords":"10.9023774, 76.9017478"
  },
  {
    "title":"Royal palm",
    "coords":"10.8996830, 76.9028341"
  },
  {
    "title":"Var. Variegeta",
    "coords":"10.8997100, 76.9032827"
  },
  {
    "title":"Weeping Fig",
    "coords":"10.8995536, 76.9033266"
  },
  {
    "title":"Bamboo",
    "coords":"10.8993854, 76.9036233"
  },
  {
    "title":"Purple orchild tree",
    "coords":"10.8994246, 76.9035690"
  },
  {
    "title":"Indian beech tree",
    "coords":"10.8995543, 76.9036183"
  },
  {
    "title":"Indian almond",
    "coords":"10.8995876, 76.9036531"
  },
  {
    "title":"Pink trumpet tree",
    "coords":"10.8996741, 76.9036122"
  },
  {
    "title":"Neem, Margosa",
    "coords":"10.8997146, 76.9036438"
  },
  {
    "title":"Silver Oak",
    "coords":"10.8997462, 76.9035915"
  },
  {
    "title":"Indian butter tree",
    "coords":"10.8997914, 76.9036052"
  },
  {
    "title":"Haldu",
    "coords":"10.8995899, 76.9034704"
  },
  {
    "title":"Cannon-ball tree",
    "coords":"10.8996718, 76.9034661"
  },
  {
    "title":"Flame of the forest",
    "coords":"10.8997400, 76.9034785"
  },
  {
    "title":"Peacock chaste tree",
    "coords":"10.8998816, 76.9034714"
  },
  {
    "title":"Indian Tupil tree",
    "coords":"10.8999665, 76.9034483"
  },
  {
    "title":"Purple orchild tree",
    "coords":"10.8999033, 76.9036347"
  },
  {
    "title":"Arjun tree",
    "coords":"10.8999342, 76.9036994"
  },
  {
    "title":"Indian tulip tree",
    "coords":"10.8999655, 76.9036555"
  },
  {
    "title":"Jack tree",
    "coords":"10.9000314, 76.9036837"
  },
  {
    "title":"Ceylon satinwood",
    "coords":"10.9000350, 76.9036310"
  },
  {
    "title":"Ceylon satinwood",
    "coords":"10.9001357, 76.9035539"
  },
  {
    "title":"Neem, Margosa",
    "coords":"10.9002299, 76.9035542"
  },
  {

  "title":"Sausage tree",
  "coords":"10.9034619, 76.9023204"

  },
  {
  "title":"Child life tree",
  "coords":"10.9034550, 76.9023627"

  },
  {
    "title":"Beech wood",
    "coords":"10.9034566, 76.9023791"
  },
  {
    "title":"Malabar blackwood",
    "coords":"10.9034553, 76.9022681"
  },
  {
    "title":"Indian beach tree",
    "coords":"10.9035732, 76.9022245"
  },
  {
    "title":"Indian king tree",
    "coords":"10.9029736, 76.9018098"
  },
  {
    "title":"African tulip tree",
    "coords":"10.9029391, 76.9018205"
  },
  {
    "title":"Spanish cherry",
    "coords":"10.9029364, 76.9018497"
  },
  {
    "title":"Pala indigo plant",
    "coords":"10.9028406, 76.9019533"
  },
  {
    "title":"Arjun tree",
    "coords":"10.9032183, 76.9016878"
  },
    {
    "title":"Indian tulip tree",
    "coords":"10.9030675, 76.9017156"
  },
  {
    "title":"Big leaf mahogany",
    "coords":"10.9031182, 76.9017887"
  },
  {
    "title":"Yellow trumpet",
    "coords":"10.9031574, 76.9019315"
  },
  {
    "title":"Katsagon",
    "coords":"10.9029012, 76.9020656"
  },
  {
    "title":"Alo vera Bunch",
    "coords":"10.9030619, 76.9020606"
  },
  {
    "title":"Soapnut",
    "coords":"10.9030945, 76.9019711"
  },
  {
    "title":"Spanish cherry",
    "coords":"10.9031412, 76.9019436"
  },
  {
    "title":"Indian cork tree",
    "coords":"10.9032051, 76.9019476"
  },
  {
    "title":"Fiddle wood",
    "coords":"10.9033753, 76.9019573"
  },
  {
    "title":"Teak",
    "coords":"10.9035053, 76.9020613"
  },
  {
    "title":"Beggers bowl(calabash tree)",
    "coords":"10.9035047, 76.9019831"
  },
  {
    "title":"Hill mango",
    "coords":"10.9036759, 76.9019090"
  },
  {
    "title":"Indian butter tree",
    "coords":"10.9036021, 76.9016170"
  },
  {
    "title":"tamarind",
    "coords":"10.9036568, 76.9016572 "
  },
  {
    "title":"Alo Vera group",
    "coords":"10.9036311, 76.9017488"
  },
  {
    "title":"Indian mulberry",
    "coords":"10.9035998, 76.9016998"
  },
  {
    "title":"Sandal",
    "coords":"10.9036670, 76.9015989"
  },
  {
    "title":"Indian tulip tree",
    "coords":"10.9039050, 76.9017052"
  },
  {
    "title":"Jambul,jamun",
    "coords":"10.9038372, 76.9016301"
  },
  {
    "title":"Indian mulberry",
    "coords":"10.9037315, 76.9016814"
  },
  {
    "title":"Indian butter tree",
    "coords":"10.9037605, 76.9017639"
  },
  {
    "title":"Veppu",
    "coords":"10.9039636, 76.9019982"
  },
  {
    "title":"Veppu",
    "coords":"10.9038306, 76.9021595"
  },
  {
    "title":"Three leaved chaste tree",
    "coords":"10.9037002, 76.9021625"
  },
  {
    "title":"Three leaved chaste tree",
    "coords":"10.9037002, 76.9023154"
  },
  {
    "title":"Pink  trumpet tree",
    "coords":"10.9037068, 76.9023553"
  },
  {
    "title":"Veppu",
    "coords":"10.9037743, 76.9023409"
  },
  {
    "title":"Veppu(meliaceae)",
    "coords":"10.9037911, 76.9021240"
  },
  {
    "title":"Cannon ball tree",
    "coords":"10.9037055, 76.9021555"
  },
  {
    "title":"Chlid life tree",
    "coords":"10.9036976, 76.9020267"
  },
  {
    "title":"Gold apple",
    "coords":"10.9038273, 76.9019258"
  },
  {
    "title":"Yellow trumpet",
    "coords":"10.9038161, 76.9018618"
  },
  {
    "title":"Gum Arabic",
    "coords":"10.9041068, 76.9023486"
  },
  {
    "title":"Red sandalwood",
    "coords":"10.9039429, 76.9024331"
  },
  {
    "title":"Indian gooseberry",
    "coords":"10.9041605, 76.9024270"
  },
  {
    "title":"Alchorn tree",
    "coords":"10.9041803, 76.9023972"
  },
  {
    "title":"Bitter albizia",
    "coords":"10.9043626, 76.9024016"
  },
  {
    "title":"Chebulic myrobalan",
    "coords":"10.9043771, 76.9023385"
  },
  {
    "title":"Three leaved chase tree",
    "coords":"10.9043942, 76.9023543"
  },
  {
    "title":"indain tulip tree",
    "coords":"10.9044344, 76.9024140"
  },
  {
    "title":"Indian beech tree",
    "coords":"10.9043281, 76.9024207"
  },
  {
    "title":"black murdar",
    "coords":"10.9041151, 76.9024220"
  },
  {
    "title":"arjun tree",
    "coords":"10.9041348, 76.9023707"
  },
  {
    "title":"beech wood",
    "coords":"10.9041770, 76.9022695"
  },  
  {
    "title":"Fala indigo plant",
    "coords":"10.9043198, 76.9015751"
  },
  {
    "title":"Lebbreck tree",
    "coords":"10.9045325, 76.9015553"
  },
  {
    "title":"neem",
    "coords":"10.9042415, 76.9014785"
  },
  {
    "title":"Catpus",

    "coords":"10.9035824, 76.8990870"
  },
  {
    "title":"Mango",
    "coords":"10.9034734, 76.8992406"
  },
  {
    "title":"Mango",
    "coords":"10.9038053, 76.8991239"
  },
  {
    "title":"Neem",
    "coords":"10.9040575, 76.8989817"
  },
  {
    "title":"Neem",
    "coords":"10.9040555, 76.8988862"
  },
  {
    "title":"Mango",
    "coords":"10.9039001, 76.8989972"
  },
  {
    "title":"Mango",
    "coords":"10.9038494, 76.8989901"
  },
  {
    "title":"Mango",
    "coords":"10.9038026, 76.8989687"
  },
  {
    "title":"Mango",
    "coords":"10.9037763, 76.8989556"
  },
  {
    "title":"Lauraceae",
    "coords":"10.9035419, 76.8987380"
  },
  {
    "title":"Lauraceae",
    "coords":"10.9035765, 76.8987061"
  },
  {
    "title":"Lauraceae",
    "coords":"10.9035264, 76.8986854"
  },
  {
    "title":"Mango",
    "coords":"10.9035053, 76.8987548 "
  },
  {
    "title":"Neem",
    "coords":"10.9036186, 76.8987031"
  },
  {
    "title":"Mango",
    "coords":"10.9037075, 76.8985191"
  },
  {
    "title":"Mango",
    "coords":"10.9037062, 76.8985965"
  },
  {
    "title":"Casuarina",
    "coords":"10.9035205, 76.8981694"
  },
  {
    "title":"Neem",
    "coords":"10.9034625, 76.8980993"
  }
]